llm_echo.py
llm_echo-0.2.dist-info/licenses/LICENSE
llm_echo-0.2.dist-info/METADATA
llm_echo-0.2.dist-info/WHEEL
llm_echo-0.2.dist-info/entry_points.txt
llm_echo-0.2.dist-info/top_level.txt
llm_echo-0.2.dist-info/RECORD
