Metadata-Version: 2.4
Name: llm-echo
Version: 0.2
Summary: Debug plugin for LLM
Author: Simon Willison
License-Expression: Apache-2.0
Project-URL: Homepage, https://github.com/simonw/llm-echo
Project-URL: Changelog, https://github.com/simonw/llm-echo/releases
Project-URL: Issues, https://github.com/simonw/llm-echo/issues
Project-URL: CI, https://github.com/simonw/llm-echo/actions
Requires-Python: >=3.9
License-File: LICENSE
Requires-Dist: llm
Provides-Extra: test
Requires-Dist: pytest; extra == "test"
Requires-Dist: pytest-asyncio; extra == "test"
Dynamic: license-file
